{
  "post": {
    "id": "47e63212-f892-4720-8cf8-15506c0b3d5c",
    "orgId": "org_demo",
    "authorId": "c3d4e5f6-a7b8-4c9d-0e1f-2a3b4c5d6e7f",
    "title": "How to Throw a Great Bachelor Party in Austin",
    "slug": "how-to-throw-great-bachelor-party-austin",
    "content": "\n        <h2>Why Austin is the Ultimate Bachelor Party Destination</h2>\n        <p>When it comes to planning an epic bachelor party, Austin, Texas stands in a league of its own. From the legendary nightlife on 6th Street to the pristine waters of Lake Travis, Austin offers the perfect blend of adventure, entertainment, and southern hospitality that makes for an unforgettable guys' weekend.</p>\n        \n        <h2>The Complete Bachelor Party Planning Guide</h2>\n        <p>Planning a successful <strong>bachelor party in Austin</strong> requires booking key activities 2-3 months in advance, especially during peak season (March-October). Start with your centerpiece activity—a Lake Travis party boat cruise—then build your itinerary around it. Book accommodations near downtown to minimize transportation hassles and maximize party time.</p>\n        \n        <h2>Top Activities for Your Austin Bachelor Party</h2>\n        \n        <h3>Lake Travis Party Boat Adventure</h3>\n        <p>No Austin bachelor party is complete without a private party boat cruise on Lake Travis. Picture this: you and your crew on a fully-equipped party boat, cruising crystal-clear waters with cold drinks, great music, and Texas sunshine. Our <strong>Lake Travis party boats</strong> accommodate 14-75 guests and include everything you need: experienced captain and crew, premium sound system, floating water mat, and unlimited fun. It's the bachelor party experience your groom will never forget.</p>\n        \n        <h3>TopGolf Austin</h3>\n        <p>Combine competition, drinks, and entertainment at TopGolf. Their climate-controlled bays, full-service restaurant, and rooftop terrace make it perfect for bachelor party groups. Book a VIP suite for your crew.</p>\n        \n        <h3>Austin Brewery Tours</h3>\n        <p>Austin's craft beer scene is world-class. Book a brewery tour through Jester King, Live Oak, or Austin Beerworks. Many companies offer party bus packages that handle transportation between breweries—perfect for bachelor parties.</p>\n        \n        <h3>6th Street Nightlife</h3>\n        <p>The legendary 6th Street entertainment district is bachelor party central. Start at Kung Fu Saloon for games and drinks, hit Rain for a nightclub experience, and end at Blind Pig for live music. VIP table service is available at most venues.</p>\n        \n        <h2>Austin's Best Food for Bachelor Parties</h2>\n        <p>Fuel your bachelor party with Austin's incredible food scene. Start with breakfast tacos from Torchy's or Veracruz All Natural. For lunch, hit <strong>Franklin BBQ</strong> (arrive at 9am to beat the line) or Salt Lick in Driftwood for family-style BBQ with unlimited sides. Dinner options include Fogo de Chão Brazilian Steakhouse for unlimited meat, or Perry's Steakhouse for their famous pork chop. Late-night munchies? P. Terry's or Whataburger never disappoint.</p>\n        \n        <h2>Where to Stay: Bachelor Party Accommodations</h2>\n        <p>Downtown Austin hotels like the W Austin or Fairmont Austin offer luxury and proximity to nightlife. For larger groups, consider renting a house in East Austin or near Zilker Park through Airbnb or VRBO. Many properties feature pools, game rooms, and outdoor spaces perfect for pre-gaming.</p>\n        \n        <h2>Budget Breakdown: Cost Per Person</h2>\n        <p>Expect to budget $600-1,000 per person for a 2-3 day Austin bachelor party:</p>\n        <ul>\n          <li>Accommodations: $150-250 per night</li>\n          <li>Lake Travis party boat: $100-200 per person</li>\n          <li>Dining and drinks: $200-300</li>\n          <li>Activities (TopGolf, breweries): $100-150</li>\n          <li>Nightlife (cover charges, drinks): $100-200</li>\n          <li>Transportation: $50-100</li>\n        </ul>\n        \n        <h2>The Perfect Austin Bachelor Party Weekend</h2>\n        \n        <h3>Friday: Arrival & Appetizer</h3>\n        <ul>\n          <li>3pm: Check-in and settle into accommodations</li>\n          <li>5pm: Happy hour at Easy Tiger or Better Half</li>\n          <li>7pm: Dinner at Fogo de Chão or Perry's Steakhouse</li>\n          <li>9pm: 6th Street bar crawl starting at Kung Fu Saloon</li>\n          <li>Midnight: Late-night food at P. Terry's</li>\n        </ul>\n        \n        <h3>Saturday: Main Event</h3>\n        <ul>\n          <li>10am: Breakfast tacos and recovery at Juan in a Million</li>\n          <li>12pm: <strong>Lake Travis Party Boat Cruise (3-4 hours)</strong></li>\n          <li>4pm: Back to hotel, rest and refresh</li>\n          <li>7pm: BBQ feast at Franklin, Terry Black's, or Salt Lick</li>\n          <li>9pm: Rainey Street bar hop</li>\n          <li>11pm: Club scene at Rain or Barbarella</li>\n        </ul>\n        \n        <h3>Sunday: Recovery & Farewell</h3>\n        <ul>\n          <li>11am: Brunch at Kerbey Lane or Snooze</li>\n          <li>1pm: TopGolf or brewery tour (for those still standing)</li>\n          <li>4pm: Farewell beers at Zilker Brewing or Live Oak</li>\n          <li>6pm: Departure</li>\n        </ul>\n        \n        <h2>Book Your Austin Bachelor Party Boat Today</h2>\n        <p>Ready to plan the ultimate bachelor party? Start with a Lake Travis party boat cruise that will be the highlight of your weekend. <a href=\"/\">Contact Premier Party Cruises</a> to reserve your date and create an unforgettable Austin bachelor party experience. We'll handle the boat, you handle the celebration!</p>\n      ",
    "contentType": "html",
    "status": "published",
    "excerpt": "Plan an epic Austin bachelor party with this complete guide featuring Lake Travis boat cruises, TopGolf, brewery tours, BBQ, nightlife, and detailed itinerary.",
    "publishedAt": "2025-10-03T09:54:15.351Z",
    "scheduledFor": null,
    "metaTitle": "Austin Bachelor Party Guide | Lake Travis Boats & Activities",
    "metaDescription": "Ultimate Austin bachelor party guide: Lake Travis boats, TopGolf, BBQ, 6th Street nightlife, budget tips & complete weekend itinerary for guys.",
    "focusKeyphrase": "bachelor party Austin",
    "featuredImage": "/attached_assets/bachelor-party-group-guys-optimized.webp",
    "featuredImageAlt": null,
    "socialImage": null,
    "readingTime": null,
    "wordCount": 673,
    "viewCount": 0,
    "featured": false,
    "allowComments": true,
    "sticky": false,
    "galleryImages": [],
    "videoUrl": null,
    "audioUrl": null,
    "customFields": {},
    "createdAt": "2025-10-03T09:54:15.351Z",
    "updatedAt": "2026-04-02T18:24:25.703Z",
    "author": {
      "id": "c3d4e5f6-a7b8-4c9d-0e1f-2a3b4c5d6e7f",
      "orgId": "org_demo",
      "name": "Premier Party Cruises",
      "slug": "emily-chen",
      "email": null,
      "bio": "Austin's premier party boat cruise company since 2009",
      "avatarUrl": "https://api.dicebear.com/7.x/avataaars/svg?seed=Emily",
      "socialLinks": {},
      "active": true,
      "displayOrder": 3,
      "createdAt": "2025-10-26T09:53:46.974Z",
      "updatedAt": "2025-10-26T09:53:46.974Z"
    },
    "categories": [
      {
        "id": "1596c60c-5fe2-482d-afde-c1805cc5d37b",
        "orgId": "org_demo",
        "name": "Bachelor Parties",
        "slug": "bachelor-parties",
        "description": "Tips, guides, and ideas for unforgettable bachelor parties in Austin",
        "parentId": null,
        "metaTitle": null,
        "metaDescription": null,
        "active": true,
        "displayOrder": 0,
        "postCount": 0,
        "createdAt": "2025-10-03T09:43:36.685Z",
        "updatedAt": "2025-10-03T09:43:36.685Z"
      },
      {
        "id": "07dca670-fc1d-4d65-b34f-636d5728f36d",
        "orgId": "org_demo",
        "name": "Austin Travel",
        "slug": "austin-travel",
        "description": "Your guide to Austin's best attractions, dining, and entertainment",
        "parentId": null,
        "metaTitle": null,
        "metaDescription": null,
        "active": true,
        "displayOrder": 0,
        "postCount": 0,
        "createdAt": "2025-10-03T09:43:36.787Z",
        "updatedAt": "2025-10-03T09:43:36.787Z"
      },
      {
        "id": "653cf793-3824-4767-9949-897d0c6d3092",
        "orgId": "org_demo",
        "name": "Party Planning",
        "slug": "party-planning",
        "description": "Expert tips and strategies for planning memorable celebrations",
        "parentId": null,
        "metaTitle": null,
        "metaDescription": null,
        "active": true,
        "displayOrder": 0,
        "postCount": 0,
        "createdAt": "2025-10-03T09:43:36.790Z",
        "updatedAt": "2025-10-03T09:43:36.790Z"
      }
    ],
    "tags": [
      {
        "id": "3ddf117c-d09e-4c24-a232-65f3af2810c6",
        "orgId": "org_demo",
        "name": "Austin",
        "slug": "austin",
        "description": "Austin, Texas",
        "active": true,
        "postCount": 0,
        "createdAt": "2025-10-03T09:43:36.851Z",
        "updatedAt": "2025-10-03T09:43:36.851Z"
      },
      {
        "id": "3ad88d98-87bd-4372-a944-fc1782d1ddf3",
        "orgId": "org_demo",
        "name": "Bachelor Party",
        "slug": "bachelor-party",
        "description": "Bachelor party planning",
        "active": true,
        "postCount": 0,
        "createdAt": "2025-10-03T09:43:36.851Z",
        "updatedAt": "2025-10-03T09:43:36.851Z"
      },
      {
        "id": "73474b3d-c946-4a4c-b6e2-61fda4c48878",
        "orgId": "org_demo",
        "name": "Lake Travis",
        "slug": "lake-travis",
        "description": "Lake Travis water activities",
        "active": true,
        "postCount": 0,
        "createdAt": "2025-10-03T09:43:36.851Z",
        "updatedAt": "2025-10-03T09:43:36.851Z"
      },
      {
        "id": "2e78b6ea-1a82-444a-a963-d5f6090669d3",
        "orgId": "org_demo",
        "name": "Party Boat",
        "slug": "party-boat",
        "description": "Party boat cruises",
        "active": true,
        "postCount": 0,
        "createdAt": "2025-10-03T09:43:36.852Z",
        "updatedAt": "2025-10-03T09:43:36.852Z"
      },
      {
        "id": "4fd505b1-ecad-4cff-8113-52dc56ce681c",
        "orgId": "org_demo",
        "name": "Party Planning",
        "slug": "party-planning",
        "description": "Event planning tips",
        "active": true,
        "postCount": 0,
        "createdAt": "2025-10-03T09:43:36.922Z",
        "updatedAt": "2025-10-03T09:43:36.922Z"
      },
      {
        "id": "ac40286c-d1f3-44f9-877b-96e54987d413",
        "orgId": "org_demo",
        "name": "Travel Guide",
        "slug": "travel-guide",
        "description": "Travel guides and tips",
        "active": true,
        "postCount": 0,
        "createdAt": "2025-10-03T09:43:36.922Z",
        "updatedAt": "2025-10-03T09:43:36.922Z"
      }
    ]
  },
  "relatedPosts": [
    {
      "id": "cf51ce0c-aa96-4e0a-b2c5-5bac8c172474",
      "orgId": "org_demo",
      "authorId": "f5d2d3c4-ccaa-41ff-be80-4533c5baad0e",
      "title": "Why Combined Bachelor & Bachelorette Parties Are the Best of Both Worlds",
      "slug": "why-combined-bachelor-bachelorette-parties-are-the-best-of-both-worlds",
      "contentType": "html",
      "status": "published",
      "excerpt": "Traditionally, the bachelor party and bachelorette party are separate affairs – two different parties, two different plans, often happening on two different weekends. But a new tradition is emerging that flips the script: combined bachelor & bachelor...",
      "publishedAt": "2026-04-02T17:58:16.504Z",
      "scheduledFor": null,
      "metaTitle": null,
      "metaDescription": "",
      "focusKeyphrase": null,
      "featuredImage": "/attached_assets/atx-disco-cruise-party.jpg",
      "featuredImageAlt": null,
      "socialImage": null,
      "readingTime": 26,
      "wordCount": 5161,
      "viewCount": 0,
      "featured": false,
      "allowComments": true,
      "sticky": false,
      "galleryImages": [],
      "videoUrl": null,
      "audioUrl": null,
      "customFields": {},
      "createdAt": "2026-04-02T17:58:16.504Z",
      "updatedAt": "2026-04-02T18:24:26.104Z",
      "author": {
        "id": "f5d2d3c4-ccaa-41ff-be80-4533c5baad0e",
        "orgId": "org_demo",
        "name": "Premier Party Cruises",
        "slug": "premier-party-cruises",
        "email": null,
        "bio": "Austin's premier party boat company on Lake Travis, specializing in bachelor and bachelorette parties, corporate events, and celebrations.",
        "avatarUrl": null,
        "socialLinks": {},
        "active": true,
        "displayOrder": 0,
        "createdAt": "2025-10-04T08:45:32.027Z",
        "updatedAt": "2025-10-04T08:45:32.027Z"
      },
      "categories": [
        {
          "id": "78f3e75e-a0c2-4d16-910d-9a8a2b801c2b",
          "orgId": "org_demo",
          "name": "Bachelorette Parties",
          "slug": "bachelorette-parties",
          "description": "Everything you need to plan the perfect bachelorette party in Austin",
          "parentId": null,
          "metaTitle": null,
          "metaDescription": null,
          "active": true,
          "displayOrder": 0,
          "postCount": 0,
          "createdAt": "2025-10-03T09:43:36.780Z",
          "updatedAt": "2025-10-03T09:43:36.780Z"
        },
        {
          "id": "1596c60c-5fe2-482d-afde-c1805cc5d37b",
          "orgId": "org_demo",
          "name": "Bachelor Parties",
          "slug": "bachelor-parties",
          "description": "Tips, guides, and ideas for unforgettable bachelor parties in Austin",
          "parentId": null,
          "metaTitle": null,
          "metaDescription": null,
          "active": true,
          "displayOrder": 0,
          "postCount": 0,
          "createdAt": "2025-10-03T09:43:36.685Z",
          "updatedAt": "2025-10-03T09:43:36.685Z"
        },
        {
          "id": "653cf793-3824-4767-9949-897d0c6d3092",
          "orgId": "org_demo",
          "name": "Party Planning",
          "slug": "party-planning",
          "description": "Expert tips and strategies for planning memorable celebrations",
          "parentId": null,
          "metaTitle": null,
          "metaDescription": null,
          "active": true,
          "displayOrder": 0,
          "postCount": 0,
          "createdAt": "2025-10-03T09:43:36.790Z",
          "updatedAt": "2025-10-03T09:43:36.790Z"
        }
      ],
      "tags": [
        {
          "id": "6787abba-a334-44c2-91a0-c3c98b57bbbe",
          "orgId": "org_demo",
          "name": "All-Inclusive Parties",
          "slug": "all-inclusive-parties",
          "description": null,
          "active": true,
          "postCount": 0,
          "createdAt": "2025-10-04T08:45:32.530Z",
          "updatedAt": "2025-10-04T08:45:32.530Z"
        },
        {
          "id": "3ad88d98-87bd-4372-a944-fc1782d1ddf3",
          "orgId": "org_demo",
          "name": "Bachelor Party",
          "slug": "bachelor-party",
          "description": "Bachelor party planning",
          "active": true,
          "postCount": 0,
          "createdAt": "2025-10-03T09:43:36.851Z",
          "updatedAt": "2025-10-03T09:43:36.851Z"
        },
        {
          "id": "e422d23d-a63e-4195-93d2-260d256c6e9d",
          "orgId": "org_demo",
          "name": "Bachelorette Party",
          "slug": "bachelorette-party",
          "description": "Bachelorette party ideas",
          "active": true,
          "postCount": 0,
          "createdAt": "2025-10-03T09:43:36.851Z",
          "updatedAt": "2025-10-03T09:43:36.851Z"
        },
        {
          "id": "4fd505b1-ecad-4cff-8113-52dc56ce681c",
          "orgId": "org_demo",
          "name": "Party Planning",
          "slug": "party-planning",
          "description": "Event planning tips",
          "active": true,
          "postCount": 0,
          "createdAt": "2025-10-03T09:43:36.922Z",
          "updatedAt": "2025-10-03T09:43:36.922Z"
        }
      ]
    },
    {
      "id": "e40e8846-eb6c-4276-8cb1-1b3ec9c5b4b1",
      "orgId": "org_demo",
      "authorId": "f5d2d3c4-ccaa-41ff-be80-4533c5baad0e",
      "title": "Unique Bachelor Party Ideas in Austin",
      "slug": "unique-bachelor-party-ideas-in-austin",
      "contentType": "html",
      "status": "published",
      "excerpt": "So you’re in charge of planning a bachelor party in Austin? Lucky you – Austin is one of the coolest playgrounds for grown-ups in the country. Live music, great beer, outdoor adventures... this town has it all. But if you want to go beyond the cliché...",
      "publishedAt": "2026-04-02T17:58:16.322Z",
      "scheduledFor": null,
      "metaTitle": null,
      "metaDescription": "",
      "focusKeyphrase": null,
      "featuredImage": "/attached_assets/bachelor-party-group-guys-hero.webp",
      "featuredImageAlt": null,
      "socialImage": null,
      "readingTime": 8,
      "wordCount": 1512,
      "viewCount": 0,
      "featured": false,
      "allowComments": true,
      "sticky": false,
      "galleryImages": [],
      "videoUrl": null,
      "audioUrl": null,
      "customFields": {},
      "createdAt": "2026-04-02T17:58:16.322Z",
      "updatedAt": "2026-04-02T18:24:26.071Z",
      "author": {
        "id": "f5d2d3c4-ccaa-41ff-be80-4533c5baad0e",
        "orgId": "org_demo",
        "name": "Premier Party Cruises",
        "slug": "premier-party-cruises",
        "email": null,
        "bio": "Austin's premier party boat company on Lake Travis, specializing in bachelor and bachelorette parties, corporate events, and celebrations.",
        "avatarUrl": null,
        "socialLinks": {},
        "active": true,
        "displayOrder": 0,
        "createdAt": "2025-10-04T08:45:32.027Z",
        "updatedAt": "2025-10-04T08:45:32.027Z"
      },
      "categories": [
        {
          "id": "1596c60c-5fe2-482d-afde-c1805cc5d37b",
          "orgId": "org_demo",
          "name": "Bachelor Parties",
          "slug": "bachelor-parties",
          "description": "Tips, guides, and ideas for unforgettable bachelor parties in Austin",
          "parentId": null,
          "metaTitle": null,
          "metaDescription": null,
          "active": true,
          "displayOrder": 0,
          "postCount": 0,
          "createdAt": "2025-10-03T09:43:36.685Z",
          "updatedAt": "2025-10-03T09:43:36.685Z"
        },
        {
          "id": "07dca670-fc1d-4d65-b34f-636d5728f36d",
          "orgId": "org_demo",
          "name": "Austin Travel",
          "slug": "austin-travel",
          "description": "Your guide to Austin's best attractions, dining, and entertainment",
          "parentId": null,
          "metaTitle": null,
          "metaDescription": null,
          "active": true,
          "displayOrder": 0,
          "postCount": 0,
          "createdAt": "2025-10-03T09:43:36.787Z",
          "updatedAt": "2025-10-03T09:43:36.787Z"
        }
      ],
      "tags": [
        {
          "id": "3ddf117c-d09e-4c24-a232-65f3af2810c6",
          "orgId": "org_demo",
          "name": "Austin",
          "slug": "austin",
          "description": "Austin, Texas",
          "active": true,
          "postCount": 0,
          "createdAt": "2025-10-03T09:43:36.851Z",
          "updatedAt": "2025-10-03T09:43:36.851Z"
        },
        {
          "id": "3ad88d98-87bd-4372-a944-fc1782d1ddf3",
          "orgId": "org_demo",
          "name": "Bachelor Party",
          "slug": "bachelor-party",
          "description": "Bachelor party planning",
          "active": true,
          "postCount": 0,
          "createdAt": "2025-10-03T09:43:36.851Z",
          "updatedAt": "2025-10-03T09:43:36.851Z"
        },
        {
          "id": "abe63468-0030-4086-bc47-4103fe0c2170",
          "orgId": "org_demo",
          "name": "Bachelor Party Ideas",
          "slug": "bachelor-party-ideas",
          "description": null,
          "active": true,
          "postCount": 0,
          "createdAt": "2025-10-04T08:45:32.373Z",
          "updatedAt": "2025-10-04T08:45:32.373Z"
        }
      ]
    },
    {
      "id": "bf0ac155-d16e-447c-b942-81c9c8be2055",
      "orgId": "org_demo",
      "authorId": "f5d2d3c4-ccaa-41ff-be80-4533c5baad0e",
      "title": "The Ultimate Co-Ed Bash: Combined Bachelor & Bachelorette Party on Lake Travis",
      "slug": "the-ultimate-co-ed-bash-combined-bachelor-bachelorette-party-on-lake-travis",
      "contentType": "html",
      "status": "published",
      "excerpt": "Why have separate bachelor and bachelorette parties when you can join forces for one epic celebration? Combined bachelor/bachelorette parties (a.k.a. “Jack and Jill” parties or simply bach parties) are exploding in popularity lately – and for good re...",
      "publishedAt": "2026-04-02T17:58:15.979Z",
      "scheduledFor": null,
      "metaTitle": null,
      "metaDescription": "",
      "focusKeyphrase": null,
      "featuredImage": "/attached_assets/disco_fun_best2_1765193453547.jpg",
      "featuredImageAlt": null,
      "socialImage": null,
      "readingTime": 6,
      "wordCount": 1058,
      "viewCount": 0,
      "featured": false,
      "allowComments": true,
      "sticky": false,
      "galleryImages": [],
      "videoUrl": null,
      "audioUrl": null,
      "customFields": {},
      "createdAt": "2026-04-02T17:58:15.979Z",
      "updatedAt": "2026-04-02T18:24:26.026Z",
      "author": {
        "id": "f5d2d3c4-ccaa-41ff-be80-4533c5baad0e",
        "orgId": "org_demo",
        "name": "Premier Party Cruises",
        "slug": "premier-party-cruises",
        "email": null,
        "bio": "Austin's premier party boat company on Lake Travis, specializing in bachelor and bachelorette parties, corporate events, and celebrations.",
        "avatarUrl": null,
        "socialLinks": {},
        "active": true,
        "displayOrder": 0,
        "createdAt": "2025-10-04T08:45:32.027Z",
        "updatedAt": "2025-10-04T08:45:32.027Z"
      },
      "categories": [
        {
          "id": "78f3e75e-a0c2-4d16-910d-9a8a2b801c2b",
          "orgId": "org_demo",
          "name": "Bachelorette Parties",
          "slug": "bachelorette-parties",
          "description": "Everything you need to plan the perfect bachelorette party in Austin",
          "parentId": null,
          "metaTitle": null,
          "metaDescription": null,
          "active": true,
          "displayOrder": 0,
          "postCount": 0,
          "createdAt": "2025-10-03T09:43:36.780Z",
          "updatedAt": "2025-10-03T09:43:36.780Z"
        },
        {
          "id": "1596c60c-5fe2-482d-afde-c1805cc5d37b",
          "orgId": "org_demo",
          "name": "Bachelor Parties",
          "slug": "bachelor-parties",
          "description": "Tips, guides, and ideas for unforgettable bachelor parties in Austin",
          "parentId": null,
          "metaTitle": null,
          "metaDescription": null,
          "active": true,
          "displayOrder": 0,
          "postCount": 0,
          "createdAt": "2025-10-03T09:43:36.685Z",
          "updatedAt": "2025-10-03T09:43:36.685Z"
        }
      ],
      "tags": [
        {
          "id": "6787abba-a334-44c2-91a0-c3c98b57bbbe",
          "orgId": "org_demo",
          "name": "All-Inclusive Parties",
          "slug": "all-inclusive-parties",
          "description": null,
          "active": true,
          "postCount": 0,
          "createdAt": "2025-10-04T08:45:32.530Z",
          "updatedAt": "2025-10-04T08:45:32.530Z"
        },
        {
          "id": "3ad88d98-87bd-4372-a944-fc1782d1ddf3",
          "orgId": "org_demo",
          "name": "Bachelor Party",
          "slug": "bachelor-party",
          "description": "Bachelor party planning",
          "active": true,
          "postCount": 0,
          "createdAt": "2025-10-03T09:43:36.851Z",
          "updatedAt": "2025-10-03T09:43:36.851Z"
        },
        {
          "id": "e422d23d-a63e-4195-93d2-260d256c6e9d",
          "orgId": "org_demo",
          "name": "Bachelorette Party",
          "slug": "bachelorette-party",
          "description": "Bachelorette party ideas",
          "active": true,
          "postCount": 0,
          "createdAt": "2025-10-03T09:43:36.851Z",
          "updatedAt": "2025-10-03T09:43:36.851Z"
        },
        {
          "id": "73474b3d-c946-4a4c-b6e2-61fda4c48878",
          "orgId": "org_demo",
          "name": "Lake Travis",
          "slug": "lake-travis",
          "description": "Lake Travis water activities",
          "active": true,
          "postCount": 0,
          "createdAt": "2025-10-03T09:43:36.851Z",
          "updatedAt": "2025-10-03T09:43:36.851Z"
        }
      ]
    }
  ]
}