{
  "post": {
    "id": "cf51ce0c-aa96-4e0a-b2c5-5bac8c172474",
    "orgId": "org_demo",
    "authorId": "f5d2d3c4-ccaa-41ff-be80-4533c5baad0e",
    "title": "Why Combined Bachelor & Bachelorette Parties Are the Best of Both Worlds",
    "slug": "why-combined-bachelor-bachelorette-parties-are-the-best-of-both-worlds",
    "content": "<p>Traditionally, the bachelor party and bachelorette party are separate affairs – two different parties, two different plans, often happening on two different weekends. But a new tradition is emerging that flips the script: combined bachelor & bachelorette parties, where the bride, groom, and all their closest friends celebrate together. If you’ve never considered a joint bash, it might sound unorthodox, but there are some seriously compelling reasons to merge the festivities. In fact, many couples are finding that combining forces leads to double the fun with half the hassle. Here’s why a co-ed “bach” party might just be the ultimate way to party before the wedding:</p>\n<h3>1. Everyone Gets to Bond Before the Big Day</h3>\n<p>One of the sweetest perks of a joint celebration is the bonding it creates. Think about it: the bridesmaids and groomsmen (and other friends) get quality time to actually hang out together before standing on opposite sides of the aisle. By the time the wedding rolls around, the ice is broken and it feels more like one unified squad rather than “her side vs his side.” This can make the wedding itself so much more enjoyable – your college buddies will know his work friends, her sisters will have inside jokes with your brothers. A combined party is like an accelerated friendship incubator. Whether you all spend a weekend at a lake house or team up for an amazing night out in Austin, those shared memories become a foundation for new friendships. The wedding day then becomes a reunion of one big friend group, not two unfamiliar groups meeting for the first time.</p>\n<h3>2. One Epic Party Saves Time and Money</h3>\n<p>Weddings are expensive – for everyone involved. Now imagine cutting out the need for two separate bachelor/bachelorette trips. With a combined party, you’re planning one event instead of two, which can seriously save on costs. Pooling budgets means you might afford a cooler experience together than you would separately. Instead of two smaller parties settling for standard options, one larger party could, say, rent a huge boat with a DJ on Lake Travis or a swanky downtown Airbnb with a private chef, splitting the cost. Travel expenses consolidate too – friends only have to fly or drive in for one event. Plus, the couple might prefer spending one weekend partying rather than two back-to-back. It’s efficient on the calendar and on the wallet. Many vendors in Austin even offer group discounts or added perks for larger, coed groups (for example, as we mentioned, our combined party boat packages give the couple special freebies and price breaks). By combining, you’re essentially doing baller party math: two celebrations for the price of one, without feeling like you cut corners on fun.</p>\n<h3>3. It’s Inclusive and Fits Modern Friend Groups</h3>\n<p>Not every bride wants a dainty spa day, and not every groom dreams of a wild night in a strip club. Interests don’t fall along gender lines so neatly, and a joint party lets you throw out the old stereotypes. Maybe the bride and groom met through mutual friends and all hang out together normally – why force separate parties? A co-ed bash is super inclusive: friends of any gender can all be part of the fun without anyone feeling left out. This is great for friend groups that aren’t split 50/50 by gender, or for including siblings/cousins who might have otherwise been excluded due to the old “no boys at the bach” rules. It also allows couples within the friend group to celebrate together if they want. Ultimately, it’s about what the couple enjoys. If both of you love live music, you can plan that as a group; if you’re foodies, everyone can enjoy a big dinner together. The party becomes about shared interests, not traditional roles. And let’s be real – in 2026, the idea that the bride and groom must party separately is a bit outdated for a lot of people. An inclusive party just feels right for many modern couples.</p>\n<h3>4. Twice the Ideas, Half the Stress</h3>\n<p>When two planning committees join forces, you suddenly have more brains (and hands) to create an epic event. The maid of honor and best man can collaborate rather than independently planning separate itineraries. This can actually make the planning process easier and more creative. Each side brings ideas to the table: maybe one group was thinking brewery tour, the other wanted a lake day – guess what, with a combined weekend you might do both! You can split duties: one person books the accommodations, another handles activities, someone designs matching T-shirts that incorporate both the bride’s and groom’s themes (flower crown and beer mug combo, anyone?). It also spreads out the responsibility – no one person is stuck trying to entertain an entire group solo. When things are combined, people tend to be more flexible and chill with plans too, because the vibe is a big friends’ getaway versus a narrowly defined “girls night” or “guys night.” And if any curveballs come up (rainy day, venue change, etc.), you’ve got a bigger team to solve it on the fly. In short, teamwork makes the dream work, and a joint party is all about team fun.</p>\n<h3>5. Unforgettable One-of-a-Kind Memories</h3>\n<p>Finally, there’s something to be said about how downright memorable a combined bachelor/bachelorette party can be. Since it’s still relatively new and not as common, it already stands out. Your group will probably talk for years about “that time we all rented a ranch and had a massive joint party with the mechanical bull and karaoke” or “the coed river rafting trip that turned into a huge water fight.” For the couple, these are memories made together, not apart. You get to watch each other have a blast with your closest friends and share in that happiness in real time, rather than just hearing stories about it later. It can be incredibly romantic in its own way – a prelude to the wedding celebration, minus the formalities. Some couples worry a joint party means they won’t get that “last hurrah” feel, but in reality it can still be every bit as rowdy or sentimental as you want. You’re just doing it side by side with your favorite person. And if the goal of any pre-wedding party is to celebrate the couple’s next chapter, what better way than all together in one big blowout?</p>\n<p>In summary, combined bachelor and bachelorette parties offer a fresh twist that many couples are finding suits them perfectly. They foster camaraderie between friend groups, save time and money, and create a space where everyone can celebrate without boundaries. Of course, they’re not for everyone – some may still crave that separate time with just the guys or girls – but it’s worth considering if the traditional route doesn’t excite you. As with all things wedding-related, you’ve got to do what feels right for you. And if that means one giant co-ed bash, we’re here to tell you it can be absolutely incredible.</p>\n<p>Thinking of planning a joint party in Austin? We say go for it! Whether it’s a lakeside adventure with our team handling the details or a DIY weekend road trip, the world (or at least Hill Country) is your oyster. One epic party, all your loved ones, zero FOMO – that’s the combined bachelor/bachelorette way. Cheers to celebrating together! 🥂🎉</p>\n<p>ATX Disco Cruise vs. Private 14-Person Cruise: Inclusions and Pricing Comparison</p>\n<p>Both the ATX Disco Cruise and a Private Boat Cruise (up to 14 people) offer a 4-hour party on Lake Travis, but they differ in experience, inclusions, and pricing. Below is a detailed look at what you get for your money with each option, including all inclusions (vs. add-ons), and a comparison of Friday/Saturday pricing for each experience.</p>\n<p>ATX Disco Cruise (Shared Party Experience)</p>\n<p>The ATX Disco Cruise is a shared 4-hour party boat experience (March–October) where multiple groups join together on one big party barge. It’s essentially an all-inclusive bachelor/bachelorette party cruise with a fun disco theme. Here’s what you get with an ATX Disco Cruise ticket:</p>\n<p>Professional Entertainment: A live DJ is onboard spinning music for the full 4 hours, keeping the energy high, and a professional photographer is included to capture the fun (digital photos are delivered to you for free). You don’t have to hire your own entertainment – it’s built into the experience.</p>\n<p>Party Atmosphere & Extras: The cruise provides a disco dance floor, giant floats (including a legendary 25-foot custom unicorn float, exclusive to this cruise), plus multiple lily-pad water mats for swimming. Fun party supplies are included as well – think bubbles, drink koozies, name tags, and even ice-water stations to keep everyone hydrated. The boat has a clean restroom on board for comfort.</p>\n<p>BYOB with Amenities: It’s BYOB, but they’ve got you covered with coolers and ice provided for your drinks on the shared cruise. You can bring your own beverages and snacks, and there’s even an option to coordinate alcohol delivery to the marina if needed. Essentially, you just show up with your drinks – the crew handles the rest (coolers, ice, cups, etc.).</p>\n<p>Multi-Group Energy: Because it’s a shared event, you’ll be partying alongside other groups (often 50+ people total on the boat). This creates a high-energy, “big party” vibe that many guests say is hard to replicate on a private boat. The crowd is usually filled with bachelor and bachelorette parties, making for a super social atmosphere. (It’s exclusively marketed to bach groups, so everyone on board is in a celebratory mood.)</p>\n<p>Turnkey Convenience: The Disco Cruise is fully planned for you – music, entertainment, activities and backup plans are all in place. Notably, it’s the only party boat with a rain contingency plan: if weather spoils the lake day, they invoke the “Lemonade Disco” – moving the party to a downtown Austin club for the same 4 hours with the same DJ and photographer, so your celebration never gets canceled. This guarantee means zero stress about weather.</p>\n<p>Package Options: There are tiered ticket packages (Basic, Disco Queen, Super Sparkle) in some promotions, but generally the price per person varies by time slot (see pricing below). All tiers include the core amenities above; higher tiers can add things like VIP decorations, bride perks, or mimosa setups, but even the base ticket is very comprehensive. In short, your ticket price already includes virtually everything you need for an epic party – you just BYOB and enjoy.</p>\n<p>Private Boat Cruise (Up to 14 People)</p>\n<p>A Private Cruise for 14 or fewer guests is an exclusive charter of a party boat just for your group. With Premier Party Cruises, the 14-person boat (named “Day Tripper”) comes with a captain and basic amenities for a 4-hour Lake Travis cruise. Here’s what you get for your money with a standard private charter:</p>\n<p>Your Own Boat & Crew: You have the entire boat to yourselves, with a licensed captain and professional crew provided to operate the vessel safely. The charter includes all the boating essentials: fuel, safety equipment, and life jackets are covered in the base price. A private cruise is fully exclusive – no strangers, just your invitees on board.</p>\n<p>Basic Amenities: The boat features a premium Bluetooth sound system (so you can be the DJ with your own playlist) and large coolers for your drinks. The outing is BYOB as well – you bring your own beverages and food. (Ice is available, though note that on a standard private rental you may need to bring your own ice or add a package for it.) The 14-person boat has comfortable seating and a clean restroom, ensuring a comfortable ride. Lily pad float mats and other floaties are available for use when you stop to swim, so your group can relax in the water. (These may be included or small add-ons depending on the package, but they are generally available to enhance your lake time.)</p>\n<p>Customizable Experience: One big benefit of a private charter is flexibility. You can typically choose your own cruise time (any day of the week, subject to availability) and aren’t limited to the Disco Cruise schedule. The itinerary can be customized – for example, you can decide when to stop for swimming, or even specify a route or cove if you have a preference. You also set the music and vibe to whatever suits your group (since there’s no outside DJ unless you hire one). This makes private charters popular for a wider range of occasions – not just bachelor/ette parties, but also birthdays, family gatherings, corporate outings, etc., where you might want a more controlled atmosphere.</p>\n<p>Optional Add-Ons: The standard private package is more bare-bones compared to the Disco Cruise, but you can upgrade your private cruise with add-ons (at additional cost) to mimic some of those all-inclusive perks. For example, Premier offers an “Essentials” add-on (~$100 for a 14p boat) which provides party supplies and premium floats, and an “Ultimate” package (~$250 for 14p) that adds on DJ equipment, disco lighting, and a premium party setup onboard. You can also pay to have a professional DJ (+~$550) or photographer (+~$350) come along on your private cruise if you really want those services. However, these extras are not included by default – they are entirely up to you and your budget. In summary, the private charter price covers the boat, crew, and basic amenities; any “special” entertainment or decor would be an additional expense.</p>\n<p>Similarities Between the Two Experiences</p>\n<p>Despite their differences, both the Disco Cruise and a private cruise share some core features:</p>\n<p>Duration and Format: Both are typically 4-hour cruises on Lake Travis. You’ll depart from the same marina (Anderson Mill Marina in Austin) and cruise out to party spots on the lake, with time allotted for swimming and lounging on the water in both experiences.</p>\n<p>Boat Amenities: Licensed captains and safety gear are included on both, as are basics like a sound system, coolers for BYOB drinks, and an onboard restroom facility. The boats used are all part of the Premier Party Cruises fleet, so they meet the same safety standards and have similar essential equipment.</p>\n<p>BYOB Policy: Bring-your-own beverages (and food) is allowed (and encouraged) on both the private charter and the Disco Cruise. Neither option provides alcohol by default, so you’ll want to stock up for your group either way. (Premier can help coordinate alcohol delivery to the dock for convenience in both cases, or you can bring your own.) Snacks or catering can similarly be brought for either cruise type.</p>\n<p>Fun in the Water: In both experiences, the boat will anchor at a popular cove or swimming spot during the cruise so you can swim and use floats. Both the private and Disco cruises come with at least some floatation toys (noodles or lily pads) for guests to enjoy the lake. The Disco Cruise just tends to have more and bigger floats (like that unicorn) included, whereas a private rental might have a standard lily pad mat available or you can add extra floats if desired.</p>\n<p>In short, no matter which option you choose, you’re getting a four-hour Lake Travis boating adventure with a skilled crew – and plenty of time to drink, dance, and swim. The differences come down to the crowd and the extras included.</p>\n<p>Key Differences and Inclusions Comparison</p>\n<p>While both cruises share the basics, there are important differences in what’s included versus what will cost extra. Below is a comparison of the two experiences, highlighting what you get for your money and what might be “missing” in each:</p>\n<p>Group Size & Atmosphere: The Private Cruise is exclusively your group (up to 14 people) – no outsiders. This means you have privacy and control, but the energy depends solely on your friends. The ATX Disco Cruise, on the other hand, is a shared party with multiple groups (often 50+ people), creating a high-energy, club-like atmosphere onboard. The Disco Cruise’s multi-group “crowd energy” is something you won’t get on a small private boat – it’s essentially a floating party where you can mingle with other bachelor/ette squads and feed off a larger crowd’s excitement. Conversely, if you prefer a more intimate or tailored gathering, the private cruise offers that exclusivity (no strangers joining in).</p>\n<p>Music & Entertainment: Live DJ entertainment is a signature of the Disco Cruise – it comes included in your ticket price with professional DJ music throughout the trip. On a private cruise, no DJ or host is provided by default – you’ll be using the Bluetooth speakers with your own playlist, or you can hire a DJ as an add-on (~$600) if you really want one. Similarly, the Disco Cruise has fun party emcees and a built-in theme (disco), whereas a private charter’s vibe is entirely up to your group (you could bring your own theme decorations or costumes, but it’s DIY).</p>\n<p>Photography: On the Disco Cruise, a professional photographer is included and will be snapping photos of all the groups throughout the day – and you get those digital pics for free afterward. This is a big perk, as hiring a photographer independently can be expensive. On a standard private cruise, no photographer is included – you’d need to take your own pictures or pay extra (~$600) to bring one along. So, with the Disco Cruise you’ll have group photos and candids handed to you without any effort, whereas with a private boat you’re on your own for capturing memories (unless you arrange something).</p>\n<p>Floats & Water Toys: The Disco Cruise comes with an array of awesome floats at no extra charge, most famously the huge unicorn float that everyone can climb on for group photos. It also has multiple large lily pad mats and other floaties available for all guests to use freely. In a private 14-person charter, you will usually have one lily pad mat or some floats available, but the giant specialty floats (like the unicorn) are not part of a standard private rental. If you want extra or premium floats/decor on a private trip, that might come with the upgraded packages or you’d bring them yourself. Essentially, the Disco Cruise supplies a full arsenal of float toys and a floating party platform, whereas a private cruise has more basic floating amenities (fun, but not as over-the-top).</p>\n<p>Party Supplies & Extras: On the Disco Cruise, a lot of party extras are included to enhance the fun – for example, they provide bubbles, cups and koozies, name tags, and even set up things like a mimosa toast (with plastic champagne flutes) for the group if you’re celebrating a bride. They also include ice water stations so everyone stays hydrated. All those little details are part of the package. On a private cruise, such extras are not automatically included – you’d bring your own cups, decorations, etc. (If you purchase the “Essentials” add-on for a private charter, the company will provide some party supplies and maybe décor for you, but this costs extra.) In summary, the Disco Cruise is a full-service party – you just show up. A private cruise is more of a DIY affair unless you pay for upgrades.</p>\n<p>Scheduling & Flexibility: The Disco Cruise runs on a fixed schedule each week: Fridays 12–4pm, Saturdays 11am–3pm or 3:30–7:30pm (during the season March–Oct). You buy tickets for those specific slots, and it only happens on those days/times. With a private cruise, you have more flexibility in scheduling – you can often choose any start time you want (morning, afternoon, or even an evening sunset cruise) on any day of the week, as long as a boat and crew are available. You also get to decide how the 4 hours are spent (more cruising around vs. more anchoring and swimming, etc.), whereas the Disco Cruise follows a preset agenda (they’ll typically cruise to a party cove and anchor for a big dance party/swim time). If your group needs a specific date or time that isn’t a regular Disco Cruise slot – say a Sunday afternoon or a weekday – a private rental is the way to go.</p>\n<p>Cost Structure and Value: The pricing model is very different between the two. The Disco Cruise is priced per person, whereas a private charter is one flat rate for the group (up to the boat’s capacity). For smaller groups, the Disco Cruise often works out cheaper per person since you’re effectively splitting the cost with other groups onboard. For example, Disco Cruise tickets range from about $85–$105 per person depending on the time (details below). A private 14-person boat on a peak Saturday might be around $1,150 base cost (before fees) for the whole group – which, if you have 14 people, comes out to roughly $80–$110 per person (plus you still wouldn’t have the DJ/photographer included at that price). In that sense, the ATX Disco Cruise offers a lot of value for bachelor/bachelorette parties – you get a DJ, photographer, gear, etc., at a per-person rate that’s typically much lower than arranging all that privately. On the other hand, if your priority is privacy or you actually have a full group of 14 willing to split the cost, a private boat can sometimes be cost-effective without the extras. The next section breaks down the exact prices for each option on popular days.</p>\n<p>Pricing Comparison – Friday vs. Saturday</p>\n<p>To illustrate the cost difference, here are the prices for the ATX Disco Cruise vs. a Private 14-person Cruise on the common time slots:</p>\n<p>Friday 12:00–4:00 PM: The ATX Disco Cruise is $95 per person on Friday midday. This price already includes the DJ, photos, etc., but is before tax/fees (with tax and standard gratuity it comes to about $125 per person). A Private 14-person charter during a similar Friday slot costs around $649 base for 4 hours. After adding the required 8.25% tax and 20% gratuity on a private booking, that comes out to roughly $856 total for the group. In per-person terms, 14 friends on a private boat Friday would end up paying about $60–$65 each (if splitting evenly). (Note: The Disco Cruise is a premium offering on Fridays, so its per-person cost is higher than a bare-bones private rental; however, it comes with ~$3500 worth of entertainment value included that a standard private rental doesn’t have.)</p>\n<p>Saturday 11:00 AM–3:00 PM (Prime slot): The ATX Disco Cruise on early Saturday is $105 per person (base rate), which is the peak pricing due to high demand. With tax and tip, that’s about $137.80 per person all-in. A private 14-person boat on a Saturday (any 4-hour window) is at the high end of the rate range – roughly $1,149 base for 4 hours on Saturday. After tax (8.25%) and 20% tip, the private total is approximately $1,515 for the group on a Saturday. That works out to about $108 per person if split among 14 people. So for a midday Saturday, the upfront cost is similar in magnitude per person (around $105–$110 each); the big difference is what that price includes (all entertainment & extras on the Disco vs. just the boat on a private).</p>\n<p>Saturday 3:30–7:30 PM (Afternoon/Sunset slot): The Disco Cruise offers a slight discount for the later Saturday slot – it’s $85 per person base price. After adding tax, gratuity, and the booking fee, it comes out to roughly $111–$119 per person all-in. This is marketed as the best value time for the Disco Cruise, since $85 is the lowest ticket price and you still get the full 4-hour party with everything included. A private 14-person charter on Saturday afternoon would cost the same as Saturday morning (about $1,149 base, ~$1.5k with fees) – there’s no price difference between morning vs. afternoon for private rentals on that day. So, splitting a $1,515 total among 14 people, it’s around $108 each on a private. In this slot, the Disco Cruise is dramatically cheaper per person ($85 vs. effectively $108) and gives a bigger party atmosphere; it’s a good option if your group is cost-conscious but still wants the Saturday experience.</p>\n<p>Note on Additional Fees: The prices above for the Disco Cruise are per-person base rates; Premier Party Cruises usually adds the tax and gratuity at checkout for transparency (so you’ll see the “all-in” price of $111.56, $124.88, $137.81, etc. per ticket including 8.25% tax and 15% tip). There may also be a small online booking fee (via the Xola booking platform) added at checkout. For private charters, the base rates quoted do not include taxes/tip, so you must factor in +8.25% tax and typically a mandatory 20% gratuity for the crew on private bookings. Essentially, a private charter’s “all-in” cost will be about ~30% higher than the raw base rate once those are applied. The Disco Cruise ticket prices, in contrast, already account for those extra fees in the final per-person total you pay (gratuity is built into the ticket, so attendees don’t need to tip additionally on the day of the event).</p>\n<p>Unique Highlights of Each Option</p>\n<p>Both the Disco Cruise and a private cruise offer a fantastic time on the lake, but each has its own special advantages. Here’s a summary of what’s especially unique or appealing about each experience:</p>\n<h2>ATX Disco Cruise – Why It’s Special:</h2>\n<p>All-Inclusive Party: It’s a turnkey celebration – you get a professional DJ, photographer, big floats, and party supplies all included. Your group doesn’t have to worry about logistics or entertainment; everything is arranged for maximum fun. This zero-stress, all-included setup is ideal for bachelor and bachelorette groups who just want to show up and rage.</p>\n<p>High-Energy Social Vibe: The multi-group format means 50–100 partiers on one boat, dancing and partying together. The energy is through the roof – it’s like a floating day club. You’ll meet other groups, sing along together, and quite possibly make new friends. Many customers say this “energy multiplication” made it the highlight of their weekend. It’s something you simply don’t get if you’re alone on a boat.</p>\n<p>Signature Attractions: The Disco Cruise has its own flair – notably the giant unicorn float (amazing for group pics and Instagram moments), a disco-themed dance floor, and fun extras like costume accessories or swag for VIP packages. It’s a uniquely themed experience you can’t find elsewhere.</p>\n<p>Rain or Shine Guarantee: Thanks to the “Lemonade Disco” weather backup, your party is guaranteed. If rain hits, they seamlessly relocate the event to a nightclub on land with the same DJ and photographer, so the party never cancels. This is a huge perk in terms of reliability – you won’t get stranded with a last-minute rain-out, whereas a private boat would simply be canceled or rescheduled if weather is bad.</p>\n<p>Cost Value for Small Groups: For groups that don’t have a ton of people, the Disco Cruise is cost-effective for what you get. You’re tapping into a large shared party, so you pay a ticket price but gain access to amenities that would cost thousands if you tried to set them up privately. For example, a group of 6-8 people can join the disco for a few hundred bucks total, which is far cheaper (and more exciting) than renting a whole boat and hiring DJ/photographer on your own. It’s the best value option for bachelor/ette parties under ~15–20 people in most cases.</p>\n<h2>Private 14-Person Cruise – Why It’s Special:</h2>\n<p>Exclusivity and Privacy: The biggest draw of a private cruise is that it’s just your group. You have total freedom to be yourselves without unknown people around. This can be great for more low-key gatherings, family outings, or any group that wants a private space. You can customize the vibe – whether that’s a wild dance party or a relaxed chill cruise, it’s your party, your rules.</p>\n<p>Flexible and Personalized: With a private charter, you choose the schedule (any date that’s available, and start time by arrangement) and can tailor the itinerary. Want to cruise the lake for sightseeing instead of anchoring at a busy cove? You can do that. Want to spend extra time swimming or celebrate a special moment (like a sunset toast)? It’s up to you. The crew is there to facilitate whatever plans you have for the 4 hours. This flexibility makes private charters ideal for occasions like corporate events, birthdays, or mixed groups that might not all be into the bach-party craziness.</p>\n<p>Intimate Atmosphere: If you have a close-knit group, a private boat gives you quality time together without distraction. You won’t be sharing the space with strangers. This can lead to a more bonding experience for your group – you can play the games you want, use your own playlist, and converse or party freely. It’s essentially your own private venue on the water.</p>\n<p>Add Your Own Touch: On a private cruise, you’re free to bring whatever you want to enhance the experience. For instance, you can bring decorations or a custom theme for a birthday, your own elaborate drink setups, or even hire specific entertainment (like a surprise performer or your friend who DJs). The boat is like a blank canvas – the company provides the basics (boat, captain, safety), and you can create a bespoke event. If your group has specific tastes or creative ideas, a private charter accommodates that in a way a preset event like the Disco Cruise cannot.</p>\n<p>Great for Larger Groups Economically: While we focused on the 14-person boat, it’s worth noting if your party grows larger (25, 50+ people), renting a private double-decker boat might actually be the only way to keep everyone together. In those cases, the cost per person can drop closer to what the Disco Cruise costs, and you get a completely private huge party. So, private charters shine for big reunions or events where you have enough people to fill a boat – you then get the whole party just for you, which can be very memorable (and you could still add DJs or other services if you want). For 14 or fewer, a private cruise is often chosen not to save money but to get that exclusive experience or specific scheduling. It’s worth it if those factors matter to you.</p>\n<p>Conclusion: In summary, the ATX Disco Cruise is a high-energy, all-inclusive group party – perfect for those who want a hassle-free, wild time with lots of people and amenities included. You pay per person and get a ton of fun features (DJ, photographer, floats, etc.) as part of the deal. The Private 14-Person Cruise is an exclusive, tailor-made outing – ideal for groups that value privacy, flexibility, and a personalized touch, even if it means organizing some elements yourself (or adding them on). Both deliver a 4-hour Lake Travis adventure; your choice comes down to whether you’d rather join the disco fever with others or have the boat all to yourselves. Either way, you’ll be on one of Austin’s best party boats – it just depends on what style of party you’re after! 🎉</p>",
    "contentType": "html",
    "status": "published",
    "excerpt": "Traditionally, the bachelor party and bachelorette party are separate affairs – two different parties, two different plans, often happening on two different weekends. But a new tradition is emerging that flips the script: combined bachelor & bachelor...",
    "publishedAt": "2026-04-02T17:58:16.504Z",
    "scheduledFor": null,
    "metaTitle": null,
    "metaDescription": "",
    "focusKeyphrase": null,
    "featuredImage": "/attached_assets/atx-disco-cruise-party.jpg",
    "featuredImageAlt": null,
    "socialImage": null,
    "readingTime": 26,
    "wordCount": 5161,
    "viewCount": 0,
    "featured": false,
    "allowComments": true,
    "sticky": false,
    "galleryImages": [],
    "videoUrl": null,
    "audioUrl": null,
    "customFields": {},
    "createdAt": "2026-04-02T17:58:16.504Z",
    "updatedAt": "2026-04-02T18:24:26.104Z",
    "author": {
      "id": "f5d2d3c4-ccaa-41ff-be80-4533c5baad0e",
      "orgId": "org_demo",
      "name": "Premier Party Cruises",
      "slug": "premier-party-cruises",
      "email": null,
      "bio": "Austin's premier party boat company on Lake Travis, specializing in bachelor and bachelorette parties, corporate events, and celebrations.",
      "avatarUrl": null,
      "socialLinks": {},
      "active": true,
      "displayOrder": 0,
      "createdAt": "2025-10-04T08:45:32.027Z",
      "updatedAt": "2025-10-04T08:45:32.027Z"
    },
    "categories": [
      {
        "id": "78f3e75e-a0c2-4d16-910d-9a8a2b801c2b",
        "orgId": "org_demo",
        "name": "Bachelorette Parties",
        "slug": "bachelorette-parties",
        "description": "Everything you need to plan the perfect bachelorette party in Austin",
        "parentId": null,
        "metaTitle": null,
        "metaDescription": null,
        "active": true,
        "displayOrder": 0,
        "postCount": 0,
        "createdAt": "2025-10-03T09:43:36.780Z",
        "updatedAt": "2025-10-03T09:43:36.780Z"
      },
      {
        "id": "1596c60c-5fe2-482d-afde-c1805cc5d37b",
        "orgId": "org_demo",
        "name": "Bachelor Parties",
        "slug": "bachelor-parties",
        "description": "Tips, guides, and ideas for unforgettable bachelor parties in Austin",
        "parentId": null,
        "metaTitle": null,
        "metaDescription": null,
        "active": true,
        "displayOrder": 0,
        "postCount": 0,
        "createdAt": "2025-10-03T09:43:36.685Z",
        "updatedAt": "2025-10-03T09:43:36.685Z"
      },
      {
        "id": "653cf793-3824-4767-9949-897d0c6d3092",
        "orgId": "org_demo",
        "name": "Party Planning",
        "slug": "party-planning",
        "description": "Expert tips and strategies for planning memorable celebrations",
        "parentId": null,
        "metaTitle": null,
        "metaDescription": null,
        "active": true,
        "displayOrder": 0,
        "postCount": 0,
        "createdAt": "2025-10-03T09:43:36.790Z",
        "updatedAt": "2025-10-03T09:43:36.790Z"
      }
    ],
    "tags": [
      {
        "id": "6787abba-a334-44c2-91a0-c3c98b57bbbe",
        "orgId": "org_demo",
        "name": "All-Inclusive Parties",
        "slug": "all-inclusive-parties",
        "description": null,
        "active": true,
        "postCount": 0,
        "createdAt": "2025-10-04T08:45:32.530Z",
        "updatedAt": "2025-10-04T08:45:32.530Z"
      },
      {
        "id": "3ad88d98-87bd-4372-a944-fc1782d1ddf3",
        "orgId": "org_demo",
        "name": "Bachelor Party",
        "slug": "bachelor-party",
        "description": "Bachelor party planning",
        "active": true,
        "postCount": 0,
        "createdAt": "2025-10-03T09:43:36.851Z",
        "updatedAt": "2025-10-03T09:43:36.851Z"
      },
      {
        "id": "e422d23d-a63e-4195-93d2-260d256c6e9d",
        "orgId": "org_demo",
        "name": "Bachelorette Party",
        "slug": "bachelorette-party",
        "description": "Bachelorette party ideas",
        "active": true,
        "postCount": 0,
        "createdAt": "2025-10-03T09:43:36.851Z",
        "updatedAt": "2025-10-03T09:43:36.851Z"
      },
      {
        "id": "4fd505b1-ecad-4cff-8113-52dc56ce681c",
        "orgId": "org_demo",
        "name": "Party Planning",
        "slug": "party-planning",
        "description": "Event planning tips",
        "active": true,
        "postCount": 0,
        "createdAt": "2025-10-03T09:43:36.922Z",
        "updatedAt": "2025-10-03T09:43:36.922Z"
      }
    ]
  },
  "relatedPosts": [
    {
      "id": "47763ff6-31d5-4328-a711-0d0da6986a94",
      "orgId": "org_demo",
      "authorId": "f5d2d3c4-ccaa-41ff-be80-4533c5baad0e",
      "title": "Unique Bachelorette Party Ideas in Austin",
      "slug": "unique-bachelorette-party-ideas-in-austin",
      "contentType": "html",
      "status": "published",
      "excerpt": "Austin isn’t just another city for bachelorette parties – it’s basically bachelorette party heaven. Sure, you’ve heard about the amazing bars on 6th Street and the live music scene, but what if you want to do something totally unique that will have y...",
      "publishedAt": "2026-04-02T17:58:16.161Z",
      "scheduledFor": null,
      "metaTitle": null,
      "metaDescription": "",
      "focusKeyphrase": null,
      "featuredImage": "/attached_assets/dancing-party-scene.jpg",
      "featuredImageAlt": null,
      "socialImage": null,
      "readingTime": 7,
      "wordCount": 1284,
      "viewCount": 0,
      "featured": false,
      "allowComments": true,
      "sticky": false,
      "galleryImages": [],
      "videoUrl": null,
      "audioUrl": null,
      "customFields": {},
      "createdAt": "2026-04-02T17:58:16.161Z",
      "updatedAt": "2026-04-02T18:24:26.049Z",
      "author": {
        "id": "f5d2d3c4-ccaa-41ff-be80-4533c5baad0e",
        "orgId": "org_demo",
        "name": "Premier Party Cruises",
        "slug": "premier-party-cruises",
        "email": null,
        "bio": "Austin's premier party boat company on Lake Travis, specializing in bachelor and bachelorette parties, corporate events, and celebrations.",
        "avatarUrl": null,
        "socialLinks": {},
        "active": true,
        "displayOrder": 0,
        "createdAt": "2025-10-04T08:45:32.027Z",
        "updatedAt": "2025-10-04T08:45:32.027Z"
      },
      "categories": [
        {
          "id": "78f3e75e-a0c2-4d16-910d-9a8a2b801c2b",
          "orgId": "org_demo",
          "name": "Bachelorette Parties",
          "slug": "bachelorette-parties",
          "description": "Everything you need to plan the perfect bachelorette party in Austin",
          "parentId": null,
          "metaTitle": null,
          "metaDescription": null,
          "active": true,
          "displayOrder": 0,
          "postCount": 0,
          "createdAt": "2025-10-03T09:43:36.780Z",
          "updatedAt": "2025-10-03T09:43:36.780Z"
        },
        {
          "id": "07dca670-fc1d-4d65-b34f-636d5728f36d",
          "orgId": "org_demo",
          "name": "Austin Travel",
          "slug": "austin-travel",
          "description": "Your guide to Austin's best attractions, dining, and entertainment",
          "parentId": null,
          "metaTitle": null,
          "metaDescription": null,
          "active": true,
          "displayOrder": 0,
          "postCount": 0,
          "createdAt": "2025-10-03T09:43:36.787Z",
          "updatedAt": "2025-10-03T09:43:36.787Z"
        }
      ],
      "tags": [
        {
          "id": "3ddf117c-d09e-4c24-a232-65f3af2810c6",
          "orgId": "org_demo",
          "name": "Austin",
          "slug": "austin",
          "description": "Austin, Texas",
          "active": true,
          "postCount": 0,
          "createdAt": "2025-10-03T09:43:36.851Z",
          "updatedAt": "2025-10-03T09:43:36.851Z"
        },
        {
          "id": "e422d23d-a63e-4195-93d2-260d256c6e9d",
          "orgId": "org_demo",
          "name": "Bachelorette Party",
          "slug": "bachelorette-party",
          "description": "Bachelorette party ideas",
          "active": true,
          "postCount": 0,
          "createdAt": "2025-10-03T09:43:36.851Z",
          "updatedAt": "2025-10-03T09:43:36.851Z"
        },
        {
          "id": "db15b635-25d6-4aac-b783-e0ee3dc59697",
          "orgId": "org_demo",
          "name": "Bachelorette Party Ideas",
          "slug": "bachelorette-party-ideas",
          "description": null,
          "active": true,
          "postCount": 0,
          "createdAt": "2025-10-04T08:45:32.418Z",
          "updatedAt": "2025-10-04T08:45:32.418Z"
        }
      ]
    },
    {
      "id": "bf0ac155-d16e-447c-b942-81c9c8be2055",
      "orgId": "org_demo",
      "authorId": "f5d2d3c4-ccaa-41ff-be80-4533c5baad0e",
      "title": "The Ultimate Co-Ed Bash: Combined Bachelor & Bachelorette Party on Lake Travis",
      "slug": "the-ultimate-co-ed-bash-combined-bachelor-bachelorette-party-on-lake-travis",
      "contentType": "html",
      "status": "published",
      "excerpt": "Why have separate bachelor and bachelorette parties when you can join forces for one epic celebration? Combined bachelor/bachelorette parties (a.k.a. “Jack and Jill” parties or simply bach parties) are exploding in popularity lately – and for good re...",
      "publishedAt": "2026-04-02T17:58:15.979Z",
      "scheduledFor": null,
      "metaTitle": null,
      "metaDescription": "",
      "focusKeyphrase": null,
      "featuredImage": "/attached_assets/disco_fun_best2_1765193453547.jpg",
      "featuredImageAlt": null,
      "socialImage": null,
      "readingTime": 6,
      "wordCount": 1058,
      "viewCount": 0,
      "featured": false,
      "allowComments": true,
      "sticky": false,
      "galleryImages": [],
      "videoUrl": null,
      "audioUrl": null,
      "customFields": {},
      "createdAt": "2026-04-02T17:58:15.979Z",
      "updatedAt": "2026-04-02T18:24:26.026Z",
      "author": {
        "id": "f5d2d3c4-ccaa-41ff-be80-4533c5baad0e",
        "orgId": "org_demo",
        "name": "Premier Party Cruises",
        "slug": "premier-party-cruises",
        "email": null,
        "bio": "Austin's premier party boat company on Lake Travis, specializing in bachelor and bachelorette parties, corporate events, and celebrations.",
        "avatarUrl": null,
        "socialLinks": {},
        "active": true,
        "displayOrder": 0,
        "createdAt": "2025-10-04T08:45:32.027Z",
        "updatedAt": "2025-10-04T08:45:32.027Z"
      },
      "categories": [
        {
          "id": "78f3e75e-a0c2-4d16-910d-9a8a2b801c2b",
          "orgId": "org_demo",
          "name": "Bachelorette Parties",
          "slug": "bachelorette-parties",
          "description": "Everything you need to plan the perfect bachelorette party in Austin",
          "parentId": null,
          "metaTitle": null,
          "metaDescription": null,
          "active": true,
          "displayOrder": 0,
          "postCount": 0,
          "createdAt": "2025-10-03T09:43:36.780Z",
          "updatedAt": "2025-10-03T09:43:36.780Z"
        },
        {
          "id": "1596c60c-5fe2-482d-afde-c1805cc5d37b",
          "orgId": "org_demo",
          "name": "Bachelor Parties",
          "slug": "bachelor-parties",
          "description": "Tips, guides, and ideas for unforgettable bachelor parties in Austin",
          "parentId": null,
          "metaTitle": null,
          "metaDescription": null,
          "active": true,
          "displayOrder": 0,
          "postCount": 0,
          "createdAt": "2025-10-03T09:43:36.685Z",
          "updatedAt": "2025-10-03T09:43:36.685Z"
        }
      ],
      "tags": [
        {
          "id": "6787abba-a334-44c2-91a0-c3c98b57bbbe",
          "orgId": "org_demo",
          "name": "All-Inclusive Parties",
          "slug": "all-inclusive-parties",
          "description": null,
          "active": true,
          "postCount": 0,
          "createdAt": "2025-10-04T08:45:32.530Z",
          "updatedAt": "2025-10-04T08:45:32.530Z"
        },
        {
          "id": "3ad88d98-87bd-4372-a944-fc1782d1ddf3",
          "orgId": "org_demo",
          "name": "Bachelor Party",
          "slug": "bachelor-party",
          "description": "Bachelor party planning",
          "active": true,
          "postCount": 0,
          "createdAt": "2025-10-03T09:43:36.851Z",
          "updatedAt": "2025-10-03T09:43:36.851Z"
        },
        {
          "id": "e422d23d-a63e-4195-93d2-260d256c6e9d",
          "orgId": "org_demo",
          "name": "Bachelorette Party",
          "slug": "bachelorette-party",
          "description": "Bachelorette party ideas",
          "active": true,
          "postCount": 0,
          "createdAt": "2025-10-03T09:43:36.851Z",
          "updatedAt": "2025-10-03T09:43:36.851Z"
        },
        {
          "id": "73474b3d-c946-4a4c-b6e2-61fda4c48878",
          "orgId": "org_demo",
          "name": "Lake Travis",
          "slug": "lake-travis",
          "description": "Lake Travis water activities",
          "active": true,
          "postCount": 0,
          "createdAt": "2025-10-03T09:43:36.851Z",
          "updatedAt": "2025-10-03T09:43:36.851Z"
        }
      ]
    },
    {
      "id": "738dcfc4-e520-43e9-afad-c6a9069d3dc3",
      "orgId": "org_demo",
      "authorId": "f5d2d3c4-ccaa-41ff-be80-4533c5baad0e",
      "title": "Experience the Ultimate Private Bachelorette Party Cruise in Austin",
      "slug": "experience-the-ultimate-private-bachelorette-party-cruise-in-austin",
      "contentType": "html",
      "status": "published",
      "excerpt": "Austin has become the go-to destination for unforgettable bachelorette parties, and there’s no better way to celebrate than on a private party cruise on Lake Travis. Picture this: you and your best friends dancing on deck under the Texas sun, sipping...",
      "publishedAt": "2026-04-02T17:58:15.665Z",
      "scheduledFor": null,
      "metaTitle": null,
      "metaDescription": "",
      "focusKeyphrase": null,
      "featuredImage": "/attached_assets/atx-disco-cruise-party.jpg",
      "featuredImageAlt": null,
      "socialImage": null,
      "readingTime": 5,
      "wordCount": 820,
      "viewCount": 0,
      "featured": false,
      "allowComments": true,
      "sticky": false,
      "galleryImages": [],
      "videoUrl": null,
      "audioUrl": null,
      "customFields": {},
      "createdAt": "2026-04-02T17:58:15.665Z",
      "updatedAt": "2026-04-02T18:24:25.981Z",
      "author": {
        "id": "f5d2d3c4-ccaa-41ff-be80-4533c5baad0e",
        "orgId": "org_demo",
        "name": "Premier Party Cruises",
        "slug": "premier-party-cruises",
        "email": null,
        "bio": "Austin's premier party boat company on Lake Travis, specializing in bachelor and bachelorette parties, corporate events, and celebrations.",
        "avatarUrl": null,
        "socialLinks": {},
        "active": true,
        "displayOrder": 0,
        "createdAt": "2025-10-04T08:45:32.027Z",
        "updatedAt": "2025-10-04T08:45:32.027Z"
      },
      "categories": [
        {
          "id": "78f3e75e-a0c2-4d16-910d-9a8a2b801c2b",
          "orgId": "org_demo",
          "name": "Bachelorette Parties",
          "slug": "bachelorette-parties",
          "description": "Everything you need to plan the perfect bachelorette party in Austin",
          "parentId": null,
          "metaTitle": null,
          "metaDescription": null,
          "active": true,
          "displayOrder": 0,
          "postCount": 0,
          "createdAt": "2025-10-03T09:43:36.780Z",
          "updatedAt": "2025-10-03T09:43:36.780Z"
        }
      ],
      "tags": [
        {
          "id": "3ddf117c-d09e-4c24-a232-65f3af2810c6",
          "orgId": "org_demo",
          "name": "Austin",
          "slug": "austin",
          "description": "Austin, Texas",
          "active": true,
          "postCount": 0,
          "createdAt": "2025-10-03T09:43:36.851Z",
          "updatedAt": "2025-10-03T09:43:36.851Z"
        },
        {
          "id": "e422d23d-a63e-4195-93d2-260d256c6e9d",
          "orgId": "org_demo",
          "name": "Bachelorette Party",
          "slug": "bachelorette-party",
          "description": "Bachelorette party ideas",
          "active": true,
          "postCount": 0,
          "createdAt": "2025-10-03T09:43:36.851Z",
          "updatedAt": "2025-10-03T09:43:36.851Z"
        },
        {
          "id": "db15b635-25d6-4aac-b783-e0ee3dc59697",
          "orgId": "org_demo",
          "name": "Bachelorette Party Ideas",
          "slug": "bachelorette-party-ideas",
          "description": null,
          "active": true,
          "postCount": 0,
          "createdAt": "2025-10-04T08:45:32.418Z",
          "updatedAt": "2025-10-04T08:45:32.418Z"
        },
        {
          "id": "b182cb2e-c24f-49c8-b1a9-953d3b6ad63c",
          "orgId": "org_demo",
          "name": "Party Boat Austin",
          "slug": "party-boat-austin",
          "description": null,
          "active": true,
          "postCount": 0,
          "createdAt": "2025-10-04T08:45:32.463Z",
          "updatedAt": "2025-10-04T08:45:32.463Z"
        }
      ]
    }
  ]
}